rangerlite/__init__.py
rangerlite/py.typed
rangerlite/rangerlite.py
rangerlite-1.0.2.dist-info/licenses/LICENSE
rangerlite-1.0.2.dist-info/METADATA
rangerlite-1.0.2.dist-info/WHEEL
rangerlite-1.0.2.dist-info/top_level.txt
rangerlite-1.0.2.dist-info/RECORD
