Metadata-Version: 2.4
Name: rangerlite
Version: 1.0.2
Summary: A pytorch implementation of the Lookahead optimizer with RAdam as inner optimizer
Author-email: Thorsten Buss <thorsten.buss@uni-hamburg.de>
License-Expression: MIT
Project-URL: Repository, https://github.com/FLC-QU-hep/ranger-lite.git
Project-URL: Issues, https://github.com/FLC-QU-hep/ranger-lite/issues
Keywords: machine-learning,deep-learning,pytorch,optimizer,lookahead,radam
Classifier: Intended Audience :: Developers
Classifier: Operating System :: OS Independent
Classifier: Programming Language :: Python :: 3
Classifier: Programming Language :: Python :: 3.10
Classifier: Programming Language :: Python :: 3.11
Classifier: Programming Language :: Python :: 3.12
Classifier: Programming Language :: Python :: 3.13
Requires-Python: <4.0,>=3.10
License-File: LICENSE
Requires-Dist: torch<3.0.0,>=2.0.0
Dynamic: license-file
